custom_table
example_project
